sanic/__init__.py
sanic/__main__.py
sanic/__version__.py
sanic/app.py
sanic/asgi.py
sanic/blueprint_group.py
sanic/blueprints.py
sanic/compat.py
sanic/config.py
sanic/constants.py
sanic/cookies.py
sanic/errorpages.py
sanic/exceptions.py
sanic/handlers.py
sanic/headers.py
sanic/helpers.py
sanic/http.py
sanic/log.py
sanic/py.typed
sanic/reloader_helpers.py
sanic/request.py
sanic/response.py
sanic/router.py
sanic/server.py
sanic/static.py
sanic/testing.py
sanic/utils.py
sanic/views.py
sanic/websocket.py
sanic/worker.py
iSanic-20.9.2.dist-info/LICENSE
iSanic-20.9.2.dist-info/METADATA
iSanic-20.9.2.dist-info/WHEEL
iSanic-20.9.2.dist-info/entry_points.txt
iSanic-20.9.2.dist-info/top_level.txt
iSanic-20.9.2.dist-info/RECORD
