Metadata-Version: 2.1
Name: iSanic
Version: 20.9.2
Summary: A web server and web framework that's written to go fast. Build fast. Run fast.
Home-page: http://github.com/imuxin/iSanic/
Author: Sanic Community
Author-email: noreply@iCloud.com
License: MIT
Platform: any
Classifier: Development Status :: 4 - Beta
Classifier: Environment :: Web Environment
Classifier: License :: OSI Approved :: MIT License
Classifier: Programming Language :: Python :: 3.6
Classifier: Programming Language :: Python :: 3.7
Classifier: Programming Language :: Python :: 3.8
Classifier: Programming Language :: Python :: 3.9
Requires-Python: >=3.6
Requires-Dist: httptools (>=0.0.10)
Requires-Dist: aiofiles (>=0.6.0)
Requires-Dist: websockets (<9.0,>=8.1)
Requires-Dist: multidict (<6.0,>=5.0)
Requires-Dist: httpx (==0.15.4)
Requires-Dist: uvloop (>=0.5.3) ; sys_platform != "win32" and implementation_name == "cpython"
Requires-Dist: ujson (>=1.35) ; sys_platform != "win32" and implementation_name == "cpython"
Provides-Extra: all
Requires-Dist: pytest (==5.2.1) ; extra == 'all'
Requires-Dist: multidict (<6.0,>=5.0) ; extra == 'all'
Requires-Dist: gunicorn (==20.0.4) ; extra == 'all'
Requires-Dist: pytest-cov ; extra == 'all'
Requires-Dist: httpcore (==0.11.*) ; extra == 'all'
Requires-Dist: beautifulsoup4 ; extra == 'all'
Requires-Dist: pytest-sanic ; extra == 'all'
Requires-Dist: pytest-sugar ; extra == 'all'
Requires-Dist: pytest-benchmark ; extra == 'all'
Requires-Dist: aiofiles ; extra == 'all'
Requires-Dist: tox ; extra == 'all'
Requires-Dist: black ; extra == 'all'
Requires-Dist: flake8 ; extra == 'all'
Requires-Dist: bandit ; extra == 'all'
Requires-Dist: towncrier ; extra == 'all'
Requires-Dist: sphinx (>=2.1.2) ; extra == 'all'
Requires-Dist: sphinx-rtd-theme ; extra == 'all'
Requires-Dist: recommonmark (>=0.5.0) ; extra == 'all'
Requires-Dist: docutils ; extra == 'all'
Requires-Dist: pygments ; extra == 'all'
Requires-Dist: uvloop (>=0.5.3) ; (sys_platform != "win32" and implementation_name == "cpython") and extra == 'all'
Requires-Dist: ujson (>=1.35) ; (sys_platform != "win32" and implementation_name == "cpython") and extra == 'all'
Provides-Extra: dev
Requires-Dist: pytest (==5.2.1) ; extra == 'dev'
Requires-Dist: multidict (<6.0,>=5.0) ; extra == 'dev'
Requires-Dist: gunicorn (==20.0.4) ; extra == 'dev'
Requires-Dist: pytest-cov ; extra == 'dev'
Requires-Dist: httpcore (==0.11.*) ; extra == 'dev'
Requires-Dist: beautifulsoup4 ; extra == 'dev'
Requires-Dist: pytest-sanic ; extra == 'dev'
Requires-Dist: pytest-sugar ; extra == 'dev'
Requires-Dist: pytest-benchmark ; extra == 'dev'
Requires-Dist: aiofiles ; extra == 'dev'
Requires-Dist: tox ; extra == 'dev'
Requires-Dist: black ; extra == 'dev'
Requires-Dist: flake8 ; extra == 'dev'
Requires-Dist: bandit ; extra == 'dev'
Requires-Dist: towncrier ; extra == 'dev'
Requires-Dist: uvloop (>=0.5.3) ; (sys_platform != "win32" and implementation_name == "cpython") and extra == 'dev'
Requires-Dist: ujson (>=1.35) ; (sys_platform != "win32" and implementation_name == "cpython") and extra == 'dev'
Provides-Extra: docs
Requires-Dist: sphinx (>=2.1.2) ; extra == 'docs'
Requires-Dist: sphinx-rtd-theme ; extra == 'docs'
Requires-Dist: recommonmark (>=0.5.0) ; extra == 'docs'
Requires-Dist: docutils ; extra == 'docs'
Requires-Dist: pygments ; extra == 'docs'
Provides-Extra: test
Requires-Dist: pytest (==5.2.1) ; extra == 'test'
Requires-Dist: multidict (<6.0,>=5.0) ; extra == 'test'
Requires-Dist: gunicorn (==20.0.4) ; extra == 'test'
Requires-Dist: pytest-cov ; extra == 'test'
Requires-Dist: httpcore (==0.11.*) ; extra == 'test'
Requires-Dist: beautifulsoup4 ; extra == 'test'
Requires-Dist: pytest-sanic ; extra == 'test'
Requires-Dist: pytest-sugar ; extra == 'test'
Requires-Dist: pytest-benchmark ; extra == 'test'
Requires-Dist: uvloop (>=0.5.3) ; (sys_platform != "win32" and implementation_name == "cpython") and extra == 'test'
Requires-Dist: ujson (>=1.35) ; (sys_platform != "win32" and implementation_name == "cpython") and extra == 'test'
